[
  {
      "id": 1,
      "name": "React Recoil",
      "boilerPlate": "suvelocity/recoil-boilerplate",
      "description": "https://github.com/suvelocity/recoil-boilerplate",
      "type": "client-only",
      "repositoryName": "suvelocity/recoil-challenge",
      "authorId": 1,
      "state": "approved",
      "createdAt": "2020-10-01T20:00:00.000Z",
      "updatedAt": "2020-10-29T08:03:21.000Z",
      "deletedAt": null,
      "Author": {
          "userName": "suvelocity"
      },
      "Labels": [
          {
              "name": "React",
              "id": 1
          },
          {
              "name": "JavaScript",
              "id": 4
          }
      ],
      "averageRaiting": "4",
      "submissionsCount": 1
  },
  {
      "id": 2,
      "name": "React - 4 In A Row",
      "boilerPlate": "suvelocity/4In-a-row-BOILERPLATE",
      "description": "https://github.com/suvelocity/4In-a-row-BOILERPLATE",
      "type": "client-only",
      "repositoryName": "suvelocity/4In-a-row-CHALLENGE",
      "authorId": 1,
      "state": "approved",
      "createdAt": "2020-10-01T20:00:00.000Z",
      "updatedAt": "2020-10-29T08:03:22.000Z",
      "deletedAt": null,
      "Author": {
          "userName": "suvelocity"
      },
      "Labels": [
          {
              "name": "React",
              "id": 1
          },
          {
              "name": "JavaScript",
              "id": 4
          }
      ],
      "averageRaiting": "3.5000",
      "submissionsCount": 1
  },
  {
      "id": 3,
      "name": "React - Calculator",
      "boilerPlate": "suvelocity/calculator-challenge",
      "description": "https://github.com/suvelocity/calculator-challenge",
      "type": "client-only",
      "repositoryName": "suvelocity/calculator-challange-tests",
      "authorId": 1,
      "state": "approved",
      "createdAt": "2020-10-01T20:00:00.000Z",
      "updatedAt": "2020-10-29T08:03:24.000Z",
      "deletedAt": null,
      "Author": {
          "userName": "suvelocity"
      },
      "Labels": [
          {
              "name": "React",
              "id": 1
          },
          {
              "name": "JavaScript",
              "id": 4
          }
      ],
      "averageRaiting": "2.0000",
      "submissionsCount": 1
  },
  {
      "id": 4,
      "name": "React - Tv shows",
      "boilerPlate": "suvelocity/TV-shows-boilerplate",
      "description": "tomer: https://github.com/suvelocity/TV-shows-boilerplate",
      "type": "client-only",
      "repositoryName": "suvelocity/TV-shows-challenge",
      "authorId": 1,
      "state": "approved",
      "createdAt": "2020-10-01T20:00:00.000Z",
      "updatedAt": "2020-10-29T08:03:25.000Z",
      "deletedAt": null,
      "Author": {
          "userName": "suvelocity"
      },
      "Labels": [
          {
              "name": "React",
              "id": 1
          },
          {
              "name": "JavaScript",
              "id": 4
          }
      ],
      "averageRaiting": null,
      "submissionsCount": 0
  },
  {
      "id": 5,
      "name": "React - Chat app",
      "boilerPlate": "suvelocity/Chat-App-Template",
      "description": "https://github.com/suvelocity/Chat-App-Template",
      "type": "fullstack",
      "repositoryName": "suvelocity/Chat_App-Challange",
      "authorId": 1,
      "state": "approved",
      "createdAt": "2020-10-01T20:00:00.000Z",
      "updatedAt": "2020-10-29T08:03:27.000Z",
      "deletedAt": null,
      "Author": {
          "userName": "suvelocity"
      },
      "Labels": [
          {
              "name": "React",
              "id": 1
          },
          {
              "name": "Node",
              "id": 2
          },
          {
              "name": "Express",
              "id": 3
          },
          {
              "name": "JavaScript",
              "id": 4
          }
      ],
      "averageRaiting": null,
      "submissionsCount": 0
  },
  {
      "id": 6,
      "name": "Js - Drag N Scale",
      "boilerPlate": "suvelocity/DragAndScaleBoilerplate",
      "description": "https://github.com/suvelocity/DragAndScaleBoilerplate",
      "type": "client-only",
      "repositoryName": "suvelocity/drag-n-scale",
      "authorId": 1,
      "state": "approved",
      "createdAt": "2020-10-01T20:00:00.000Z",
      "updatedAt": "2020-10-29T08:03:28.000Z",
      "deletedAt": null,
      "Author": {
          "userName": "suvelocity"
      },
      "Labels": [
          {
              "name": "JavaScript",
              "id": 4
          },
          {
              "name": "HTML",
              "id": 5
          },
          {
              "name": "CSS",
              "id": 6
          }
      ],
      "averageRaiting": null,
      "submissionsCount": 0
  }
]